LICENCE
README.md
setup.py
tkini/__init__.py
tkini/_types.py
tkini/_utils.py
tkini/tkinter_widgets.py
tkini/widget_grid_settings.py
tkini.egg-info/PKG-INFO
tkini.egg-info/SOURCES.txt
tkini.egg-info/dependency_links.txt
tkini.egg-info/requires.txt
tkini.egg-info/top_level.txt