Metadata-Version: 2.1
Name: tkini
Version: 0.3.2
Summary: TkIni é uma biblioteca construída em cima do Tkinter para simplificar a criação de GUIs em Python. Ele permite a leitura de estilos e configurações de widgets a partir de arquivos de texto e oferece uma interface para definir eventos personalizados e manipuladores de eventos para widgets.
Home-page: https://github.com/1marcuth/tkini
Author: Marcuth
Author-email: example@gmail.com
Requires-Python: >=3.11
License-File: LICENCE
